.gitignore
.pre-commit-config.yaml
.readthedocs.yaml
CMakeLists.txt
LICENSE
MANIFEST.in
README.md
environment.yml
pyproject.toml
requirements.txt
rtd_environment.yml
setup.py
.github/ISSUE_TEMPLATE/bug_report.md
.github/ISSUE_TEMPLATE/feature_request.md
.github/workflows/main.yml
.github/workflows/publish.yml
docs/Makefile
docs/make.bat
docs/source/changelog.rst
docs/source/conf.py
docs/source/getting_started.rst
docs/source/index.rst
docs/source/installation.rst
docs/source/_static/favicon.ico
docs/source/_static/logo.svg
docs/source/_templates/version.html
docs/source/_templates/autosummary/attribute.rst
docs/source/_templates/autosummary/base.rst
docs/source/_templates/autosummary/class.rst
docs/source/_templates/autosummary/function.rst
docs/source/_templates/autosummary/method.rst
docs/source/_templates/autosummary/property.rst
docs/source/first_steps/index.rst
docs/source/reference/index.rst
docs/source/user_guide/index.rst
extensions/_kalpy.cpp
extensions/chain/chain.cpp
extensions/chain/pybind_chain.h
extensions/cudamatrix/cudamatrix.cpp
extensions/cudamatrix/pybind_cudamatrix.h
extensions/decoder/decoder.cpp
extensions/decoder/pybind_decoder.h
extensions/feat/feat.cpp
extensions/feat/pybind_feat.h
extensions/fstext/fstext.cpp
extensions/fstext/pybind_fstext.h
extensions/gmm/gmm.cpp
extensions/gmm/pybind_gmm.h
extensions/hmm/hmm.cpp
extensions/hmm/pybind_hmm.h
extensions/itf/itf.cpp
extensions/itf/pybind_itf.h
extensions/ivector/ivector.cpp
extensions/ivector/pybind_ivector.h
extensions/kws/kws.cpp
extensions/kws/pybind_kws.h
extensions/lat/lat.cpp
extensions/lat/pybind_lat.h
extensions/lm/lm.cpp
extensions/lm/pybind_lm.h
extensions/matrix/matrix.cpp
extensions/matrix/pybind_matrix.h
extensions/nnet/nnet.cpp
extensions/nnet/pybind_nnet.h
extensions/nnet2/nnet2.cpp
extensions/nnet2/pybind_nnet2.h
extensions/nnet3/nnet3.cpp
extensions/nnet3/pybind_nnet3.h
extensions/online/online.cpp
extensions/online/pybind_online.h
extensions/online2/online2.cpp
kalpy_kaldi.egg-info/PKG-INFO
kalpy_kaldi.egg-info/SOURCES.txt
kalpy_kaldi.egg-info/dependency_links.txt
kalpy_kaldi.egg-info/not-zip-safe
kalpy_kaldi.egg-info/requires.txt
kalpy_kaldi.egg-info/top_level.txt
