Metadata-Version: 2.4
Name: kalpy-kaldi
Version: 0.9.0
Summary: Pybind11 bindings for Kaldi for use with the Montreal Forced Aligner
Author: Michael McAuliffe
Author-email: michael.e.mcauliffe@gmail.com
License: MIT
Requires-Python: >=3.7
License-File: LICENSE
Provides-Extra: test
Requires-Dist: pytest>=6.0; extra == "test"
Dynamic: author
Dynamic: author-email
Dynamic: description
Dynamic: description-content-type
Dynamic: license
Dynamic: license-file
Dynamic: provides-extra
Dynamic: requires-python
Dynamic: summary
